video_clip/__init__.py
video_clip/video_clip.py
video_clip/video_llama/__init__.py
video_clip/video_llama/common/__init__.py
video_clip/video_llama/common/config.py
video_clip/video_llama/common/dist_utils.py
video_clip/video_llama/common/gradcam.py
video_clip/video_llama/common/logger.py
video_clip/video_llama/common/optims.py
video_clip/video_llama/common/registry.py
video_clip/video_llama/common/utils.py
video_clip/video_llama/conversation_/__init__.py
video_clip/video_llama/conversation_/conversation_video.py
video_clip/video_llama/datasets/__init__.py
video_clip/video_llama/datasets/data_utils.py
video_clip/video_llama/datasets/builders/__init__.py
video_clip/video_llama/datasets/builders/base_dataset_builder.py
video_clip/video_llama/datasets/builders/image_text_pair_builder.py
video_clip/video_llama/datasets/builders/instruct_builder.py
video_clip/video_llama/datasets/builders/video_caption_builder.py
video_clip/video_llama/datasets/datasets/__init__.py
video_clip/video_llama/datasets/datasets/askyoutube_datasets.py
video_clip/video_llama/datasets/datasets/base_dataset.py
video_clip/video_llama/datasets/datasets/caption_datasets.py
video_clip/video_llama/datasets/datasets/cc_sbu_dataset.py
video_clip/video_llama/datasets/datasets/dataloader_utils.py
video_clip/video_llama/datasets/datasets/laion_dataset.py
video_clip/video_llama/datasets/datasets/llava_instruct_dataset.py
video_clip/video_llama/datasets/datasets/video_instruct_dataset.py
video_clip/video_llama/datasets/datasets/webvid_datasets.py
video_clip/video_llama/models/Qformer.py
video_clip/video_llama/models/__init__.py
video_clip/video_llama/models/base_model.py
video_clip/video_llama/models/blip2.py
video_clip/video_llama/models/blip2_outputs.py
video_clip/video_llama/models/eva_vit.py
video_clip/video_llama/models/modeling_llama.py
video_clip/video_llama/models/video_llama.py
video_clip/video_llama/models/ImageBind/data.py
video_clip/video_llama/models/ImageBind/models/__init__.py
video_clip-0.2.0.dist-info/METADATA
video_clip-0.2.0.dist-info/WHEEL
video_clip-0.2.0.dist-info/top_level.txt
video_clip-0.2.0.dist-info/RECORD
