Metadata-Version: 2.1
Name: video-clip
Version: 0.2.0
Summary: AskVideos-VideoCLIP model
Home-page: https://github.com/AskYoutubeAI/AskVideos-VideoCLIP
Author: AskVideos
Author-email: askutubeai@gmail.com
Requires-Python: >=3.6
Requires-Dist: transformers
Requires-Dist: torch
Requires-Dist: numpy
Requires-Dist: decord
Requires-Dist: torchvision
Requires-Dist: omegaconf
Requires-Dist: iopath
Requires-Dist: timm
Requires-Dist: webdataset
Requires-Dist: einops
Requires-Dist: pandas
Requires-Dist: opencv-python
Requires-Dist: scipy
